pwutils
