Metadata-Version: 1.1
Name: django-pwutils
Version: 0.1.10
Summary: Django specific utils and helpers
Home-page: http://bitbucket.org/suvitorg/django-pwutils
Author: Suvit Org
Author-email: mail@suvit.ru
License: MIT
Platform: UNKNOWN
Classifier: Development Status :: 5 - Production/Stable
Classifier: Framework :: Django
Classifier: License :: OSI Approved :: MIT License
Classifier: Intended Audience :: Developers
Classifier: Intended Audience :: System Administrators
Classifier: Operating System :: OS Independent
Classifier: Programming Language :: Python
Classifier: Programming Language :: Python :: 2.6
Classifier: Programming Language :: Python :: 2.7
Classifier: Environment :: Web Environment
Classifier: Topic :: Software Development
